filemanager/__init__.py
filemanager/filemanager.py
filemanager/config/__init__.py
filemanager/config/filemanager.py
filemanager/constants/__init__.py
filemanager/controllers/filemanager_controller.py
filemanager/drivers/filemanager_driver.py
filemanager/drivers/local_driver.py
filemanager/drivers/s3_driver.py
filemanager/providers/__init__.py
filemanager/providers/filemanager_provider.py
filemanager/resources/__init__.py
filemanager/resources/dropzone.min.css
filemanager/resources/dropzone.min.js
filemanager/resources/glightbox.min.css
filemanager/resources/glightbox.min.js
filemanager/resources/picker.css
filemanager/resources/picker.js
filemanager/routes/__init__.py
filemanager/routes/route.py
filemanager/templates/details.html
filemanager/templates/index.html
filemanager/templates/picker.html
filemanager/templates/sidebar.html
filemanager/templates/partials/create_form.html
filemanager/templates/partials/dialog.html
filemanager/templates/partials/grid.html
filemanager/templates/partials/list.html
filemanager/templates/partials/rename_form.html
filemanager/templates/partials/previews/audio.html
filemanager/templates/partials/previews/file.html
filemanager/templates/partials/previews/image.html
filemanager/templates/partials/previews/pdf.html
filemanager/templates/partials/previews/video.html
masonite_filemanager-0.1.3.dist-info/LICENSE
masonite_filemanager-0.1.3.dist-info/METADATA
masonite_filemanager-0.1.3.dist-info/WHEEL
masonite_filemanager-0.1.3.dist-info/top_level.txt
masonite_filemanager-0.1.3.dist-info/RECORD
